src/traffic_controller.v
module traffic_controller (
    input clock,
    input reset,
    input emergency_a,
    input emergency_b,

    output reg a_green,
    output reg a_yellow,
    output reg a_red,

    output reg b_green,
    output reg b_yellow,
    output reg b_red
);

//state encoding 
parameter s0=2'b00;
parameter s1=2'b01;
parameter s2=2'b10;
parameter s3=2'b11;

// to store counters and current state 
reg [3:0] counter;
reg[1:0] state;

always @(posedge clock or posedge reset) begin
    if (reset) begin
        state <=0;
        counter <=4'd0;
    end
    else if (emergency_a && emergency_b) begin
        state <= s0;
        counter <= 4'd0;
    end
    else if (emergency_a) begin
        state <= s0;
        counter <=4'd0;
    end
    else if (emergency_b) begin
        state <= s2;
        counter <=4'd0;
    end
    //fsm
    else begin
        counter <= counter + 1'b1;
    end
    case (state)
        s0: begin
            if (counter==10) begin
                state <= s1;
                counter <= 4'd0;
            end
        end 
        s1: begin
            if (counter==4) begin
                state <= s2;
                counter <= 4'd0;
            end
        end
        s2: begin
            if (counter==10) begin
                state<=s3;
                counter <= 4'd0;
            end
        end
        s3:begin
            if (counter==4) begin
                state <= s0;
                counter <= 4'd0;
            end
        end
     
    endcase
end

// output logic
always @(*) begin
    a_green=0;a_red=0;a_yellow=0;
    b_green=0;b_red=0;b_yellow=0;

    case (state)
        s0:begin
            a_green=1;
            b_red=1;
        end 
        s1: begin
            a_yellow=1;
            b_red=1;
        end
        s2: begin
            a_red=1;
            b_green=1;
        end
        s3:begin
            a_red=1;
            b_yellow=1;
        end
    
         
    endcase

end

endmodule

src/traffic_controller_tb.v
`timescale 1ns/1ps
module traffic_controller_tb;
reg clock,reset,emergency_a,emergency_b;
wire a_green,a_red,a_yellow,b_green,b_red,b_yellow;

traffic_controller DUT(
    .clock(clock),
    .reset(reset),
    .emergency_a(emergency_a),
    .emergency_b(emergency_b),
    .a_green(a_green),
    .a_yellow(a_yellow),
    .a_red(a_red),
    .b_red(b_red),
    .b_green(b_green),
    .b_yellow(b_yellow)
);

always #5 clock = ~clock;

initial begin
    $dumpfile("traffic_controller.vcd");
    $dumpvars(0,traffic_controller_tb);

    //system initialize 
    clock=0;
    reset=1;
    emergency_a=0;
    emergency_b=0;

    #12 reset = 0;

    #50;

    //test cases
    emergency_a=1;#10;
    emergency_b=0; #10;

    emergency_a=0;#10;
    emergency_b=1;#10;

    emergency_a=1;#10;
    emergency_b=1;#10 ; 

$finish;

end
endmodule

waveform file/traffic_controller.vcd
$date
	Sat Apr 18 23:32:04 2026
$end
$version
	Icarus Verilog
$end
$timescale
	1ps
$end
$scope module traffic_controller_tb $end
$var wire 1 ! b_yellow $end
$var wire 1 " b_red $end
$var wire 1 # b_green $end
$var wire 1 $ a_yellow $end
$var wire 1 % a_red $end
$var wire 1 & a_green $end
$var reg 1 ' clock $end
$var reg 1 ( emergency_a $end
$var reg 1 ) emergency_b $end
$var reg 1 * reset $end
$scope module DUT $end
$var wire 1 ' clock $end
$var wire 1 ( emergency_a $end
$var wire 1 ) emergency_b $end
$var wire 1 * reset $end
$var parameter 2 + s0 $end
$var parameter 2 , s1 $end
$var parameter 2 - s2 $end
$var parameter 2 . s3 $end
$var reg 1 & a_green $end
$var reg 1 % a_red $end
$var reg 1 $ a_yellow $end
$var reg 1 # b_green $end
$var reg 1 " b_red $end
$var reg 1 ! b_yellow $end
$var reg 4 / counter [3:0] $end
$var reg 2 0 state [1:0] $end
$upscope $end
$upscope $end
$enddefinitions $end
$comment Show the parameter values. $end
$dumpall
b11 .
b10 -
b1 ,
b0 +
$end
#0
$dumpvars
b0 0
b0 /
1*
0)
0(
0'
1&
0%
0$
0#
1"
0!
$end
#5000
1'
#10000
0'
#12000
0*
#15000
b1 /
1'
#20000
0'
#25000
b10 /
1'
#30000
0'
#35000
b11 /
1'
#40000
0'
#45000
b100 /
1'
#50000
0'
#55000
b101 /
1'
#60000
0'
#62000
1(
#65000
b0 /
1'
#70000
0'
#75000
1'
#80000
0'
#82000
0(
#85000
b1 /
1'
#90000
0'
#92000
1)
#95000
1#
1%
0"
0&
b0 /
b10 0
1'
#100000
0'
#102000
1(
#105000
1"
1&
0#
0%
b0 0
1'
